{
  "personal": {
    "name": "Hermes Pérez",
    "title": "Tech Lead | Senior Full Stack Developer | Computer Engineer",
    "location": "Bogotá, Colombia (Remote)",
    "email": "hermes.perez@example.com",
    "linkedin": "linkedin.com/in/hermes-perez",
    "phone": "+57 XXX XXX XXXX"
  },
  "summary": "Computer Engineer with over 8 years of experience leading high-performance teams and developing scalable software solutions. Specialist in modern architectures (React, Node.js, Next.js) with extensive experience as Tech Lead and Technology Director. Expert in optimizing the software development lifecycle (SDLC), implementing automated testing (Jest), and leading technical transformation in agile environments. Focused on delivering high-quality technical products and strategic alignment with business objectives.",
  "experience": [
    {
      "id": "jump-cube-2024",
      "company": "Jump Cube Technologies",
      "position": "Tech Lead",
      "startDate": "2024-11",
      "endDate": null,
      "location": "Bogotá (Remote)",
      "description": "Technical leadership of complex projects using React, Node.js and cloud architectures.",
      "highlights": [
        "Technical leadership of complex projects using React, Node.js and cloud architectures",
        "Mentoring development teams and making decisions about infrastructure and technology stack",
        "Workflow optimization through CI/CD and comprehensive code reviews"
      ],
      "technologies": ["React", "Node.js", "TypeScript", "AWS", "CI/CD"]
    },
    {
      "id": "bti-lab-2022",
      "company": "BTI (BTi Lab)",
      "position": "Front-End Tech Lead / Director / Tech Lead",
      "startDate": "2022-03",
      "endDate": "2024-11",
      "location": "Bogotá (Remote)",
      "description": "Constant evolution from Tech Lead to Area Director, managing IT strategy and department KPIs.",
      "highlights": [
        "Constant evolution from Tech Lead to Area Director, managing IT strategy and department KPIs",
        "Front-End architecture definition for multiple projects using Next.js, TypeScript and Angular",
        "Implementation of Unit Testing methodologies (Jest) to ensure software stability",
        "Technical negotiation with stakeholders and infrastructure budget management in GCP and Amazon CloudFront"
      ],
      "technologies": [
        "Next.js",
        "TypeScript",
        "Angular",
        "Jest",
        "GCP",
        "Amazon CloudFront"
      ]
    },
    {
      "id": "tutenlabs-2021",
      "company": "Tutenlabs",
      "position": "Full Stack Developer",
      "startDate": "2021-08",
      "endDate": "2022-03",
      "location": "Remote",
      "description": "Comprehensive application development using Functional Programming and microservices architectures.",
      "highlights": [
        "Comprehensive application development using Functional Programming and microservices architectures",
        "NoSQL database management and software infrastructure optimization"
      ],
      "technologies": [
        "Node.js",
        "Functional Programming",
        "Microservices",
        "NoSQL"
      ]
    },
    {
      "id": "shokworks-2020",
      "company": "Shokworks, Inc.",
      "position": "Front-End Developer",
      "startDate": "2020-06",
      "endDate": "2022-03",
      "location": "Remote",
      "description": "Development of advanced user interfaces with React.js and GraphQL.",
      "highlights": [
        "Development of advanced user interfaces with React.js and GraphQL",
        "Ensuring cross-browser compatibility and performance optimization (SEO/PWA)"
      ],
      "technologies": ["React.js", "GraphQL", "SEO", "PWA"]
    },
    {
      "id": "nelumbo-2017",
      "company": "Nelumbo",
      "position": "Full Stack Developer",
      "startDate": "2017-06",
      "endDate": "2020-12",
      "location": "Cúcuta, Colombia",
      "description": "Development of robust applications using JavaScript, PHP (Laravel) and PostgreSQL.",
      "highlights": [
        "Development of robust applications using JavaScript, PHP (Laravel) and PostgreSQL",
        "Implementation of MVC design patterns and deployment of scalable solutions for various sectors"
      ],
      "technologies": ["JavaScript", "PHP", "Laravel", "PostgreSQL", "MVC"]
    }
  ],
  "skills": [
    {
      "category": "Frontend",
      "skills": [
        { "name": "React.js", "level": 5, "years": 6 },
        { "name": "Next.js", "level": 5, "years": 4 },
        { "name": "Angular", "level": 4, "years": 3 },
        { "name": "TypeScript", "level": 5, "years": 5 },
        { "name": "HTML5/CSS3", "level": 5, "years": 8 },
        { "name": "SASS", "level": 4, "years": 4 }
      ]
    },
    {
      "category": "Backend",
      "skills": [
        { "name": "Node.js", "level": 5, "years": 6 },
        { "name": "Express.js", "level": 5, "years": 5 },
        { "name": "Python", "level": 4, "years": 3 },
        { "name": "PHP", "level": 4, "years": 4 },
        { "name": "Laravel", "level": 4, "years": 3 }
      ]
    },
    {
      "category": "Databases",
      "skills": [
        { "name": "MongoDB", "level": 4, "years": 4 },
        { "name": "PostgreSQL", "level": 4, "years": 5 }
      ]
    },
    {
      "category": "Cloud & DevOps",
      "skills": [
        { "name": "Amazon CloudFront", "level": 4, "years": 2 },
        { "name": "Google Cloud Platform", "level": 4, "years": 2 },
        { "name": "Git/GitHub", "level": 5, "years": 8 },
        { "name": "CI/CD", "level": 4, "years": 3 }
      ]
    },
    {
      "category": "Testing & Quality",
      "skills": [
        { "name": "Jest", "level": 4, "years": 3 },
        { "name": "Unit Testing", "level": 4, "years": 4 },
        { "name": "Code Review", "level": 5, "years": 5 }
      ]
    },
    {
      "category": "Architecture",
      "skills": [
        { "name": "SOA", "level": 4, "years": 3 },
        { "name": "MVC", "level": 5, "years": 6 },
        { "name": "Microservices", "level": 4, "years": 3 },
        { "name": "PWA", "level": 4, "years": 2 }
      ]
    }
  ],
  "education": [
    {
      "degree": "Computer Engineering",
      "institution": "Universidad Nacional Experimental del Táchira (UNET)",
      "startYear": 2011,
      "endYear": 2018,
      "location": "Venezuela"
    }
  ],
  "lastUpdated": "2025-01-13"
}
